setup.py
pyspark_postgresql_utils/__init__.py
pyspark_postgresql_utils.egg-info/PKG-INFO
pyspark_postgresql_utils.egg-info/SOURCES.txt
pyspark_postgresql_utils.egg-info/dependency_links.txt
pyspark_postgresql_utils.egg-info/not-zip-safe
pyspark_postgresql_utils.egg-info/top_level.txt