Metadata-Version: 1.0
Name: pyspark-postgresql-utils
Version: 0.0.1
Summary: Usefull functions for working with PostgreSQL in PySpark
Home-page: https://github.com/osahp/pyspark_postgresql_utils
Author: Smelov Vladimir
Author-email: vladimirfol@gmail.com
License: UNKNOWN
Platform: UNKNOWN
